opencv_compare/__init__.py
opencv_compare/__main__.py
opencv_compare/tools.py
opencv_compare-0.0.3.dist-info/LICENSE
opencv_compare-0.0.3.dist-info/METADATA
opencv_compare-0.0.3.dist-info/WHEEL
opencv_compare-0.0.3.dist-info/top_level.txt
opencv_compare-0.0.3.dist-info/RECORD
