Metadata-Version: 2.1
Name: opencv-compare
Version: 0.0.3
Summary: A simple image comparison tool, in OpenCV
Home-page: https://github.com/sjjeong94/opencv-compare
Author: sjjeong94
Author-email: sjjeong94@gmail.com
License: MIT
License-File: LICENSE
Requires-Dist: opencv-python
